snowtrail/__init__.py
snowtrail/__main__.py
snowtrail/_client.py
snowtrail/_products.py
snowtrail/check_setup.py
snowtrail/py.typed
snowtrail-0.1.2.dist-info/METADATA
snowtrail-0.1.2.dist-info/WHEEL
snowtrail-0.1.2.dist-info/RECORD
