Metadata-Version: 2.4
Name: snowtrail
Version: 0.1.2
Summary: Python SDK for Snowtrail Research API - commodities intelligence for systematic trading.
Project-URL: Homepage, https://snowtrail.ai
Project-URL: Documentation, https://docs.snowtrail.ai
Project-URL: API, https://api.snowtrail.ai/docs
Author-email: Snowtrail Research <support@snowtrail.ai>
License: Proprietary
Keywords: api,commodities,energy,natural-gas,signals,trading
Classifier: Development Status :: 4 - Beta
Classifier: Intended Audience :: Financial and Insurance Industry
Classifier: Operating System :: OS Independent
Classifier: Programming Language :: Python :: 3
Classifier: Programming Language :: Python :: 3.9
Classifier: Programming Language :: Python :: 3.10
Classifier: Programming Language :: Python :: 3.11
Classifier: Programming Language :: Python :: 3.12
Classifier: Topic :: Office/Business :: Financial :: Investment
Classifier: Typing :: Typed
Requires-Python: >=3.9
Requires-Dist: pandas<3.0.0,>=2.0.0
Requires-Dist: requests<3.0.0,>=2.28.0
Provides-Extra: dev
Requires-Dist: mypy>=1.10.0; extra == 'dev'
Requires-Dist: pytest-cov>=4.0.0; extra == 'dev'
Requires-Dist: pytest>=8.0.0; extra == 'dev'
Requires-Dist: ruff>=0.4.0; extra == 'dev'
Requires-Dist: types-requests>=2.31.0; extra == 'dev'
